adminrestrict/__init__.py
adminrestrict/admin.py
adminrestrict/middleware.py
adminrestrict/models.py
adminrestrict/signals.py
adminrestrict/test_settings.py
adminrestrict/test_urls.py
adminrestrict/tests.py
adminrestrict/migrations/0001_initial.py
adminrestrict/migrations/__init__.py
django_adminrestrict-3.0.dist-info/LICENSE
django_adminrestrict-3.0.dist-info/METADATA
django_adminrestrict-3.0.dist-info/WHEEL
django_adminrestrict-3.0.dist-info/top_level.txt
django_adminrestrict-3.0.dist-info/RECORD
