Metadata-Version: 2.1
Name: django-adminrestrict
Version: 3.0
Summary: Restrict admin pages using simple IP address rules
Home-page: https://github.com/robromano/django-adminrestrict
Author: Robert Romano
Author-email: rromano@example.com
License: MIT
Keywords: authentication,django,security
Platform: UNKNOWN
Classifier: Development Status :: 5 - Production/Stable
Classifier: Environment :: Web Environment
Classifier: Framework :: Django
Classifier: Intended Audience :: Developers
Classifier: Intended Audience :: System Administrators
Classifier: License :: OSI Approved :: MIT License
Classifier: Operating System :: OS Independent
Classifier: Programming Language :: Python
Classifier: Programming Language :: Python :: 2.7
Classifier: Programming Language :: Python :: 3
Classifier: Topic :: Internet :: Log Analysis
Classifier: Topic :: Internet :: WWW/HTTP :: WSGI :: Middleware
Classifier: Topic :: Security
Classifier: Topic :: System :: Logging
